torchslide-0.3.0.data/purelib/torchslide/__init__.py
torchslide-0.3.0.data/purelib/torchslide/bin/__init__.py
torchslide-0.3.0.data/purelib/torchslide/bin/_multiresolutionimageinterface.so
torchslide-0.3.0.data/purelib/torchslide/bin/multiresolutionimageinterface.py
torchslide-0.3.0.data/purelib/torchslide/bin/formats/libopenslidefileformat.so
torchslide-0.3.0.data/purelib/torchslide/lib/__init__.py
torchslide-0.3.0.data/purelib/torchslide/lib/libannotation.so
torchslide-0.3.0.data/purelib/torchslide/lib/libcore.so
torchslide-0.3.0.data/purelib/torchslide/lib/libjpeg2kcodec.so
torchslide-0.3.0.data/purelib/torchslide/lib/libmultiresolutionimageinterface.so
torchslide-0.3.0.dist-info/LICENSE
torchslide-0.3.0.dist-info/METADATA
torchslide-0.3.0.dist-info/WHEEL
torchslide-0.3.0.dist-info/top_level.txt
torchslide-0.3.0.dist-info/RECORD
