Metadata-Version: 2.1
Name: torchslide
Version: 0.3.0
Summary: torchslide - prebuilt version for Python 3.6
Home-page: https://github.com/arquolo/torchslide-bin
Author: Paul Maevskikh
Author-email: arquolo@gmail.com
License: UNKNOWN
Platform: UNKNOWN
Classifier: Development Status :: 3 - Alpha
Classifier: Programming Language :: Python :: 3
Classifier: Programming Language :: Python :: 3.6
Classifier: License :: OSI Approved :: MIT License
Classifier: Operating System :: Microsoft :: Windows
Classifier: Operating System :: POSIX :: Linux
Requires-Python: >=3.6, <3.7
Requires-Dist: dataclasses
Requires-Dist: numpy (>=1.15)
